README.md
pyproject.toml
setup.cfg
setup.py
src/fit2gpx.py
src/fit2gpx.egg-info/PKG-INFO
src/fit2gpx.egg-info/SOURCES.txt
src/fit2gpx.egg-info/dependency_links.txt
src/fit2gpx.egg-info/requires.txt
src/fit2gpx.egg-info/top_level.txt