Metadata-Version: 2.1
Name: fit2gpx
Version: 1.0.0
Summary: Package to convert .FIT files to .GPX files, including tools for .FIT files downloaded from Strava
Home-page: https://github.com/dodo-saba/fit2gpx
Author: Dorian Sabathier
Author-email: dorian.sabathier+PyPi@gmail.com
License: GNU AGPLv3
Download-URL: https://github.com/dodo-saba/fit2gpx/archive/refs/tags/v1.0.0.tar.gz
Keywords: convert,.fit,fit,.gpx,gpx,strava
Platform: UNKNOWN
Classifier: Development Status :: 5 - Production/Stable
Classifier: Intended Audience :: Developers
Classifier: Intended Audience :: Other Audience
Classifier: Topic :: Scientific/Engineering :: GIS
Classifier: License :: OSI Approved :: GNU Affero General Public License v3
Classifier: Operating System :: OS Independent
Classifier: Programming Language :: Python :: 3
Classifier: Programming Language :: Python :: 3.6
Classifier: Programming Language :: Python :: 3.7
Classifier: Programming Language :: Python :: 3.8
Classifier: Programming Language :: Python :: 3.9
Classifier: Programming Language :: Python :: 3.10
Classifier: Programming Language :: Python :: 3.11
Classifier: Programming Language :: Python :: 3.12
Classifier: Programming Language :: Python :: 3.13
Requires-Python: >=3.6
